<!DOCTYPE ParticleEffect SYSTEM '../../dtd/particle_effect.dtd'>
<ParticleEffect maxParticles="32" space="Local" timeToEmit="60" name="Wisps">
    <Dampening max="1" min="1"/>
    <DirectionalForce x="0" y="0"/>
    <Emitter emissionRate="0.100" spread="0" angle="90">
        <SpawnArea width="1024" depth="0" height="768"/>
    </Emitter>
    <EndColor b="255" r="255" g="255" a="255"/>
    <Rotation max="-90" min="-90"/>
    <RotationSpeed max="0" min="0"/>
    <Size>
        <Max x="26" y="26"/>
        <Min x="26" y="26"/>
    </Size>
    <SizeChange>
        <Max x="-4.800" y="-4.800"/>
        <Min x="-4.800" y="-4.800"/>
    </SizeChange>
    <StartColor b="255" r="255" g="255" a="0"/>
    <Texture numFramesY="1" blend="Add" numFramesX="1" filename="shared/bootstrap/particles/tex/nice_spark.png"/>
    <TextureFrame numTextureAnimationFrames="0" textureAnimationSpeed="0" startFrame="0"/>
    <TimeToLive max="5.300" min="5.300"/>
    <Velocity max="10" min="5"/>
</ParticleEffect>
