<?xml version="1.0" encoding="UTF-8"?>
<!DOCTYPE Scene SYSTEM "../../../dtd/scene.dtd">
<Scene>
	<SceneObject name="BoardObject">
		<Translation z="0" />
		<!--SceneObject name="Grid"/-->
		<SceneObject name="Stencil" />
		<LayoutConfiguration name="Portrait">
			<Size>
				<Width percentage="100" />
				<Height percentage="72" />
				<OriginalSize width="700" height="700" />
			</Size>
			<Translation>
				<X percentage="50" />
				<Y percentage="50" />
			</Translation>
		</LayoutConfiguration>
		<LayoutConfiguration name="Landscape">
			<Size>
				<Height percentage="96" />
				<Width percentage="72" />
				<OriginalSize width="700" height="700" />
			</Size>
			<Translation>
				<X percentage="62" />
				<Y percentage="50" />
			</Translation>
		</LayoutConfiguration>
	</SceneObject>
</Scene>
