{"levels":[{"tileMap":[[[2,104],[2,104],[2,104],[2,104],[2,104],[2,104],[2,104],[2,104],[2,104]],[[2],[2],[2],[2],[2],[2],[2],[2],[2]],[[2],[2],[2],[2],[2],[2],[2],[2],[2]],[[2],[2],[4,3],[2],[2],[2],[4,3],[2],[2]],[[2],[2],[2],[2],[2],[2],[2],[2],[2]],[[2],[2],[2],[2],[1,2],[2],[2],[2],[2]],[[0],[53],[2],[53],[2],[53],[2],[53],[0]],[[0],[2,201,211],[54],[2,201,211],[54],[2,201,211],[54],[2,201,211],[0]],[[0],[2,201],[0],[2,201],[0],[2,201],[0],[2,201],[0]]],"numberOfItemColors":6,"gameModeName":"GiantBears","gameModeTasks":[{"name":"Bear Memory","preferredNumberOfGiantFishes":20,"preferredNumberOfGiantBears":1}],"colorWeights":{"yellow":1,"black":0,"red":1,"cyan":1,"green":1,"orange":1,"blue":1,"purple":1},"showIntroCameraScroll":false,"movesLimit":30,"protocolVersion":"7.0","portalTubes":[],"candyCannons":[{"normalType":104,"ammunition":[],"coordinate":[0,0],"colors":[]},{"normalType":104,"ammunition":[],"coordinate":[1,0],"colors":[]},{"normalType":104,"ammunition":[],"coordinate":[2,0],"colors":[]},{"normalType":104,"ammunition":[],"coordinate":[3,0],"colors":[]},{"normalType":104,"ammunition":[],"coordinate":[4,0],"colors":[]},{"normalType":104,"ammunition":[],"coordinate":[5,0],"colors":[]},{"normalType":104,"ammunition":[],"coordinate":[6,0],"colors":[]},{"normalType":104,"ammunition":[],"coordinate":[7,0],"colors":[]},{"normalType":104,"ammunition":[],"coordinate":[8,0],"colors":[]}],"portals":[],"useRandomColors":1,"maxNumLiquoriceOnScreen":0,"minNumLiquoriceOnScreen":0,"showAcceleration":0,"liquoriceSpawnRate":0,"scoreTargets":[3000,10000,20000],"reverseLevelIntroCameraScroll":false,"specialCandiesAmmunitionData":[{"spawnInterval":0,"ammunitionType":"coloring_candy","amountPerSpawn":0,"initialSpawnIntervalCounterValue":0},{"spawnInterval":0,"ammunitionType":"colorBomb","amountPerSpawn":0,"initialSpawnIntervalCounterValue":0},{"spawnInterval":0,"ammunitionType":"fish","amountPerSpawn":0,"initialSpawnIntervalCounterValue":0},{"spawnInterval":0,"ammunitionType":"horizontalStripedCandy","amountPerSpawn":0,"initialSpawnIntervalCounterValue":0},{"spawnInterval":0,"ammunitionType":"verticalStripedCandy","amountPerSpawn":0,"initialSpawnIntervalCounterValue":0},{"spawnInterval":0,"ammunitionType":"wrappedCandy","amountPerSpawn":0,"initialSpawnIntervalCounterValue":0}],"sidekickId":-1,"sidekickCollectionAmount":0,"starlevel":[3000,10000,20000],"cameraTargets":[[4,4]],"levelId":3,"preferredColors":[],"randomSeed":0,"accelerationMap":[[[0,2],[0,2],[0,2],[0,2],[0,2],[0,2],[0,2],[0,2],[0,2]],[[0,2],[0,2],[0,2],[0,2],[0,2],[0,2],[0,2],[0,2],[0,2]],[[0,2],[0,2],[0,2],[0,2],[0,2],[0,2],[0,2],[0,2],[0,2]],[[0,2],[0,2],[0,2],[0,2],[0,2],[0,2],[0,2],[0,2],[0,2]],[[0,2],[0,2],[0,2],[0,2],[0,2],[0,2],[0,2],[0,2],[0,2]],[[0,2],[0,2],[0,2],[0,2],[0,2],[0,2],[0,2],[0,2],[0,2]],[[0,0],[0,2],[0,2],[0,2],[0,2],[0,2],[0,2],[0,2],[0,0]],[[0,0],[0,2],[0,2],[0,2],[0,2],[0,2],[0,2],[0,2],[0,0]],[[0,0],[0,2],[0,0],[0,2],[0,0],[0,2],[0,0],[0,2],[0,0]]],"tutorialsToShow":[]}]}