{"levels":[{"liquoriceSpawnRate":1,"scoreTargets":[3000,60000,90000],"reverseLevelIntroCameraScroll":false,"randomSeed":0,"specialCandiesAmmunitionData":[{"initialSpawnIntervalCounterValue":0,"spawnInterval":0,"ammunitionType":"coloring_candy","amountPerSpawn":0},{"initialSpawnIntervalCounterValue":0,"spawnInterval":0,"ammunitionType":"colorBomb","amountPerSpawn":0},{"initialSpawnIntervalCounterValue":0,"spawnInterval":0,"ammunitionType":"fish","amountPerSpawn":0},{"initialSpawnIntervalCounterValue":0,"spawnInterval":0,"ammunitionType":"horizontalStripedCandy","amountPerSpawn":0},{"initialSpawnIntervalCounterValue":0,"spawnInterval":0,"ammunitionType":"verticalStripedCandy","amountPerSpawn":0},{"initialSpawnIntervalCounterValue":0,"spawnInterval":0,"ammunitionType":"wrappedCandy","amountPerSpawn":0}],"preferredColors":[],"numberOfItemColors":4,"portals":[{"coordinate":[0,4],"normal":[0,-1],"connectionId":1,"id":0},{"coordinate":[0,6],"normal":[0,1],"connectionId":0,"id":1},{"coordinate":[1,4],"normal":[0,-1],"connectionId":3,"id":2},{"coordinate":[1,6],"normal":[0,1],"connectionId":2,"id":3},{"coordinate":[2,4],"normal":[0,-1],"connectionId":5,"id":4},{"coordinate":[2,6],"normal":[0,1],"connectionId":4,"id":5},{"coordinate":[6,4],"normal":[0,-1],"connectionId":13,"id":12},{"coordinate":[6,6],"normal":[0,1],"connectionId":12,"id":13},{"coordinate":[7,4],"normal":[0,-1],"connectionId":15,"id":14},{"coordinate":[7,6],"normal":[0,1],"connectionId":14,"id":15},{"coordinate":[8,4],"normal":[0,-1],"connectionId":17,"id":16},{"coordinate":[8,6],"normal":[0,1],"connectionId":16,"id":17}],"portalTubes":[{"portalBId":1,"segmentCoordinates":[[0,4],[0,5],[0,6]],"portalAId":0},{"portalBId":3,"segmentCoordinates":[[1,4],[1,5],[1,6]],"portalAId":2},{"portalBId":5,"segmentCoordinates":[[2,4],[2,5],[2,6]],"portalAId":4},{"portalBId":13,"segmentCoordinates":[[6,4],[6,5],[6,6]],"portalAId":12},{"portalBId":15,"segmentCoordinates":[[7,4],[7,5],[7,6]],"portalAId":14},{"portalBId":17,"segmentCoordinates":[[8,4],[8,5],[8,6]],"portalAId":16}],"candyCannons":[{"coordinate":[0,0],"colors":[],"normalType":104,"ammunition":["normalItems"]},{"coordinate":[1,0],"colors":[],"normalType":104,"ammunition":["normalItems"]},{"coordinate":[2,0],"colors":[],"normalType":104,"ammunition":["normalItems"]},{"coordinate":[3,0],"colors":[],"normalType":104,"ammunition":["normalItems"]},{"coordinate":[4,0],"colors":[],"normalType":104,"ammunition":["normalItems"]},{"coordinate":[5,0],"colors":[],"normalType":104,"ammunition":["normalItems"]},{"coordinate":[6,0],"colors":[],"normalType":104,"ammunition":["normalItems"]},{"coordinate":[7,0],"colors":[],"normalType":104,"ammunition":["normalItems"]},{"coordinate":[8,0],"colors":[],"normalType":104,"ammunition":["normalItems"]},{"coordinate":[3,6],"colors":[],"normalType":104,"ammunition":["liquorice","normalItems"]},{"coordinate":[4,6],"colors":[],"normalType":104,"ammunition":["liquorice","normalItems"]},{"coordinate":[5,6],"colors":[],"normalType":104,"ammunition":["liquorice","normalItems"]}],"levelId":5,"showAcceleration":0,"accelerationMap":[[[0,2],[0,2],[0,2],[0,2],[0,2],[0,2],[0,2],[0,2],[0,2]],[[0,2],[0,2],[0,2],[0,2],[0,2],[0,2],[0,2],[0,2],[0,2]],[[0,2],[0,2],[0,2],[0,2],[0,2],[0,2],[0,2],[0,2],[0,2]],[[0,2],[0,2],[0,2],[0,2],[0,2],[0,2],[0,2],[0,2],[0,2]],[[0,2],[0,2],[0,2],[0,2],[0,2],[0,2],[0,2],[0,2],[0,2]],[[0,0],[0,0],[0,0],[0,0],[0,0],[0,0],[0,0],[0,0],[0,0]],[[0,2],[0,2],[0,2],[0,2],[0,2],[0,2],[0,2],[0,2],[0,2]],[[0,2],[0,2],[0,2],[0,2],[0,2],[0,2],[0,2],[0,2],[0,2]],[[0,2],[0,2],[0,2],[0,2],[0,2],[0,2],[0,2],[0,2],[0,2]]],"colorWeights":{"purple":1,"cyan":1,"green":1,"orange":1,"black":1.5,"red":1,"yellow":1,"blue":1},"tileMap":[[[2,104],[2,104],[2,104],[2,104],[2,104],[2,104],[2,104],[2,104],[2,104]],[[2],[2],[2],[2],[2],[2],[2],[2],[2]],[[2],[2],[2],[2],[2],[2],[2],[2],[2]],[[2],[2],[2],[2],[2],[2],[2],[2],[2]],[[2,101],[2,101],[2,101],[2],[2],[2],[2,101],[2,101],[2,101]],[[0],[0],[0],[0],[0],[0],[0],[0],[0]],[[101,2,300,505,500],[101,2,300,505],[101,2,300,505],[505,503,650,104],[505,503,650,104],[505,503,650,104],[101,2,300,505],[101,2,300,505],[101,2,300,505,500]],[[2,300,505,500],[2,300,505],[2,300,505],[505,503,650],[505,503,650],[505,503,650],[2,300,505],[2,300,505],[2,300,505,500]],[[2,300,505,500],[2,300,505,500],[2,300,505,500],[503,650,505],[505,503,650],[505,503,650],[2,300,505,500],[2,300,505,500],[2,300,505,500]]],"protocolVersion":"7.0","gameModeName":"PaintBattleMode","starlevel":[3000,60000,90000],"gameModeTasks":[{"name":"CaramelColorTakeoverTask"}],"showIntroCameraScroll":false,"movesLimit":40,"cameraTargets":[[4,4]],"useRandomColors":0,"sidekickId":-1,"maxNumLiquoriceOnScreen":15,"sidekickCollectionAmount":0,"minNumLiquoriceOnScreen":9,"tutorialsToShow":[]}]}