<?xml version='1.0' encoding='UTF-8'?>

<Scene>
  <SceneObject name="Levels2">
    <!-- Generated from Maya -->
    <SceneObject name="Level406">
      <SceneObjects>
        <Import filename="shared/diorama/common/scenes/level_button_content.xml"/>
      </SceneObjects>
      <Translation x="-600.556" y="70.554" z="57.470"/>
      <Scale x="1.0" y="-1.0" z="1.0"/>
      <Rotation x="-20"/>
      <SceneObject name="Player">
        <Translation x="61.927" y="5.869" z="3.903"/>
        <Scale x="0.8" y="0.8" z="0.8"/>
        <Import filename="shared/diorama/common/scenes/portrait/portrait_player.xml"/>
      </SceneObject>
      <SceneObject name="Friends">
        <Translation x="64.346" y="8.396" z="-6.737"/>
        <Scale x="0.8" y="0.8" z="0.8"/>
        <Import filename="shared/diorama/common/scenes/portrait/portrait_friends.xml"/>
      </SceneObject>
    </SceneObject>
    <SceneObject name="Level407">
      <SceneObjects>
        <Import filename="shared/diorama/common/scenes/level_button_content.xml"/>
      </SceneObjects>
      <Translation x="-564.252" y="62.032" z="205.780"/>
      <Scale x="1.0" y="-1.0" z="1.0"/>
      <Rotation x="-20"/>
      <SceneObject name="Player">
        <Translation x="61.928" y="5.869" z="3.903"/>
        <Scale x="0.8" y="0.8" z="0.8"/>
        <Import filename="shared/diorama/common/scenes/portrait/portrait_player.xml"/>
      </SceneObject>
      <SceneObject name="Friends">
        <Translation x="64.346" y="8.395" z="-6.737"/>
        <Scale x="0.8" y="0.8" z="0.8"/>
        <Import filename="shared/diorama/common/scenes/portrait/portrait_friends.xml"/>
      </SceneObject>
    </SceneObject>
    <SceneObject name="Level408">
      <SceneObjects>
        <Import filename="shared/diorama/common/scenes/level_button_content.xml"/>
      </SceneObjects>
      <Translation x="-389.146" y="58.039" z="208.535"/>
      <Scale x="1.0" y="-1.0" z="1.0"/>
      <Rotation x="-20"/>
      <SceneObject name="Player">
        <Translation x="61.928" y="5.869" z="3.903"/>
        <Scale x="0.8" y="0.8" z="0.8"/>
        <Import filename="shared/diorama/common/scenes/portrait/portrait_player.xml"/>
      </SceneObject>
      <SceneObject name="Friends">
        <Translation x="64.347" y="8.396" z="-6.737"/>
        <Scale x="0.8" y="0.8" z="0.8"/>
        <Import filename="shared/diorama/common/scenes/portrait/portrait_friends.xml"/>
      </SceneObject>
    </SceneObject>
    <SceneObject name="Level409">
      <SceneObjects>
        <Import filename="shared/diorama/common/scenes/level_button_content.xml"/>
      </SceneObjects>
      <Translation x="-381.405" y="56.282" z="48.374"/>
      <Scale x="1.0" y="-1.0" z="1.0"/>
      <Rotation x="-20"/>
      <SceneObject name="Player">
        <Translation x="61.928" y="5.869" z="3.903"/>
        <Scale x="0.8" y="0.8" z="0.8"/>
        <Import filename="shared/diorama/common/scenes/portrait/portrait_player.xml"/>
      </SceneObject>
      <SceneObject name="Friends">
        <Translation x="64.347" y="8.395" z="-6.737"/>
        <Scale x="0.8" y="0.8" z="0.8"/>
        <Import filename="shared/diorama/common/scenes/portrait/portrait_friends.xml"/>
      </SceneObject>
    </SceneObject>
    <SceneObject name="Level410">
      <SceneObjects>
        <Import filename="shared/diorama/common/scenes/level_button_content.xml"/>
      </SceneObjects>
      <Translation x="-201.967" y="56.282" z="47.462"/>
      <Scale x="1.0" y="-1.0" z="1.0"/>
      <Rotation x="-20"/>
      <SceneObject name="Player">
        <Translation x="61.927" y="5.869" z="3.903"/>
        <Scale x="0.8" y="0.8" z="0.8"/>
        <Import filename="shared/diorama/common/scenes/portrait/portrait_player.xml"/>
      </SceneObject>
      <SceneObject name="Friends">
        <Translation x="64.346" y="8.395" z="-6.736"/>
        <Scale x="0.8" y="0.8" z="0.8"/>
        <Import filename="shared/diorama/common/scenes/portrait/portrait_friends.xml"/>
      </SceneObject>
    </SceneObject>
    <SceneObject name="Level411">
      <SceneObjects>
        <Import filename="shared/diorama/common/scenes/level_button_content.xml"/>
      </SceneObjects>
      <Translation x="-199.158" y="56.282" z="206.624"/>
      <Scale x="1.0" y="-1.0" z="1.0"/>
      <Rotation x="-20"/>
      <SceneObject name="Player">
        <Translation x="61.928" y="5.869" z="3.903"/>
        <Scale x="0.8" y="0.8" z="0.8"/>
        <Import filename="shared/diorama/common/scenes/portrait/portrait_player.xml"/>
      </SceneObject>
      <SceneObject name="Friends">
        <Translation x="64.347" y="8.395" z="-6.736"/>
        <Scale x="0.8" y="0.8" z="0.8"/>
        <Import filename="shared/diorama/common/scenes/portrait/portrait_friends.xml"/>
      </SceneObject>
    </SceneObject>
    <SceneObject name="Level412">
      <SceneObjects>
        <Import filename="shared/diorama/common/scenes/level_button_content.xml"/>
      </SceneObjects>
      <Translation x="-28.047" y="56.282" z="203.948"/>
      <Scale x="1.0" y="-1.0" z="1.0"/>
      <Rotation x="-20"/>
      <SceneObject name="Player">
        <Translation x="61.928" y="5.869" z="3.903"/>
        <Scale x="0.8" y="0.8" z="0.8"/>
        <Import filename="shared/diorama/common/scenes/portrait/portrait_player.xml"/>
      </SceneObject>
      <SceneObject name="Friends">
        <Translation x="64.346" y="8.395" z="-6.736"/>
        <Scale x="0.8" y="0.8" z="0.8"/>
        <Import filename="shared/diorama/common/scenes/portrait/portrait_friends.xml"/>
      </SceneObject>
    </SceneObject>
    <SceneObject name="Level413">
      <SceneObjects>
        <Import filename="shared/diorama/common/scenes/level_button_content.xml"/>
      </SceneObjects>
      <Translation x="-38.770" y="56.282" z="55.516"/>
      <Scale x="1.0" y="-1.0" z="1.0"/>
      <Rotation x="-20"/>
      <SceneObject name="Player">
        <Translation x="61.928" y="5.869" z="3.903"/>
        <Scale x="0.8" y="0.8" z="0.8"/>
        <Import filename="shared/diorama/common/scenes/portrait/portrait_player.xml"/>
      </SceneObject>
      <SceneObject name="Friends">
        <Translation x="64.346" y="8.395" z="-6.736"/>
        <Scale x="0.8" y="0.8" z="0.8"/>
        <Import filename="shared/diorama/common/scenes/portrait/portrait_friends.xml"/>
      </SceneObject>
    </SceneObject>
    <SceneObject name="Level414">
      <SceneObjects>
        <Import filename="shared/diorama/common/scenes/level_button_content.xml"/>
      </SceneObjects>
      <Translation x="140.706" y="56.282" z="52.898"/>
      <Scale x="1.0" y="-1.0" z="1.0"/>
      <Rotation x="-20"/>
      <SceneObject name="Player">
        <Translation x="61.928" y="5.869" z="3.903"/>
        <Scale x="0.8" y="0.8" z="0.8"/>
        <Import filename="shared/diorama/common/scenes/portrait/portrait_player.xml"/>
      </SceneObject>
      <SceneObject name="Friends">
        <Translation x="64.346" y="8.395" z="-6.736"/>
        <Scale x="0.8" y="0.8" z="0.8"/>
        <Import filename="shared/diorama/common/scenes/portrait/portrait_friends.xml"/>
      </SceneObject>
    </SceneObject>
    <SceneObject name="Level415">
      <SceneObjects>
        <Import filename="shared/diorama/common/scenes/level_button_content.xml"/>
      </SceneObjects>
      <Translation x="140.698" y="56.282" z="194.658"/>
      <Scale x="1.0" y="-1.0" z="1.0"/>
      <Rotation x="-20"/>
      <SceneObject name="Player">
        <Translation x="61.928" y="5.869" z="3.903"/>
        <Scale x="0.8" y="0.8" z="0.8"/>
        <Import filename="shared/diorama/common/scenes/portrait/portrait_player.xml"/>
      </SceneObject>
      <SceneObject name="Friends">
        <Translation x="64.347" y="8.395" z="-6.737"/>
        <Scale x="0.8" y="0.8" z="0.8"/>
        <Import filename="shared/diorama/common/scenes/portrait/portrait_friends.xml"/>
      </SceneObject>
    </SceneObject>
    <SceneObject name="Level416">
      <SceneObjects>
        <Import filename="shared/diorama/common/scenes/level_button_content.xml"/>
      </SceneObjects>
      <Translation x="312.368" y="56.282" z="200.219"/>
      <Scale x="1.0" y="-1.0" z="1.0"/>
      <Rotation x="-20"/>
      <SceneObject name="Player">
        <Translation x="61.928" y="5.869" z="3.903"/>
        <Scale x="0.8" y="0.8" z="0.8"/>
        <Import filename="shared/diorama/common/scenes/portrait/portrait_player.xml"/>
      </SceneObject>
      <SceneObject name="Friends">
        <Translation x="64.346" y="8.395" z="-6.737"/>
        <Scale x="0.8" y="0.8" z="0.8"/>
        <Import filename="shared/diorama/common/scenes/portrait/portrait_friends.xml"/>
      </SceneObject>
    </SceneObject>
    <SceneObject name="Level417">
      <SceneObjects>
        <Import filename="shared/diorama/common/scenes/level_button_content.xml"/>
      </SceneObjects>
      <Translation x="307.037" y="56.282" z="59.740"/>
      <Scale x="1.0" y="-1.0" z="1.0"/>
      <Rotation x="-20"/>
      <SceneObject name="Player">
        <Translation x="61.927" y="5.869" z="3.903"/>
        <Scale x="0.8" y="0.8" z="0.8"/>
        <Import filename="shared/diorama/common/scenes/portrait/portrait_player.xml"/>
      </SceneObject>
      <SceneObject name="Friends">
        <Translation x="64.346" y="8.395" z="-6.737"/>
        <Scale x="0.8" y="0.8" z="0.8"/>
        <Import filename="shared/diorama/common/scenes/portrait/portrait_friends.xml"/>
      </SceneObject>
    </SceneObject>
    <SceneObject name="Level418">
      <SceneObjects>
        <Import filename="shared/diorama/common/scenes/level_button_content.xml"/>
      </SceneObjects>
      <Translation x="469.216" y="56.282" z="56.956"/>
      <Scale x="1.0" y="-1.0" z="1.0"/>
      <Rotation x="-20"/>
      <SceneObject name="Player">
        <Translation x="61.928" y="5.869" z="3.903"/>
        <Scale x="0.8" y="0.8" z="0.8"/>
        <Import filename="shared/diorama/common/scenes/portrait/portrait_player.xml"/>
      </SceneObject>
      <SceneObject name="Friends">
        <Translation x="64.347" y="8.395" z="-6.737"/>
        <Scale x="0.8" y="0.8" z="0.8"/>
        <Import filename="shared/diorama/common/scenes/portrait/portrait_friends.xml"/>
      </SceneObject>
    </SceneObject>
    <SceneObject name="Level419">
      <SceneObjects>
        <Import filename="shared/diorama/common/scenes/level_button_content.xml"/>
      </SceneObjects>
      <Translation x="485.084" y="56.282" z="213.971"/>
      <Scale x="1.0" y="-1.0" z="1.0"/>
      <Rotation x="-20"/>
      <SceneObject name="Player">
        <Translation x="61.928" y="5.869" z="3.903"/>
        <Scale x="0.8" y="0.8" z="0.8"/>
        <Import filename="shared/diorama/common/scenes/portrait/portrait_player.xml"/>
      </SceneObject>
      <SceneObject name="Friends">
        <Translation x="64.346" y="8.395" z="-6.737"/>
        <Scale x="0.8" y="0.8" z="0.8"/>
        <Import filename="shared/diorama/common/scenes/portrait/portrait_friends.xml"/>
      </SceneObject>
    </SceneObject>
    <SceneObject name="Level420">
      <SceneObjects>
        <Import filename="shared/diorama/common/scenes/level_button_content.xml"/>
      </SceneObjects>
      <Translation x="654.253" y="59.517" z="107.061"/>
      <Scale x="1.0" y="-1.0" z="1.0"/>
      <Rotation x="-20"/>
      <SceneObject name="Player">
        <Translation x="61.928" y="5.869" z="3.903"/>
        <Scale x="0.8" y="0.8" z="0.8"/>
        <Import filename="shared/diorama/common/scenes/portrait/portrait_player.xml"/>
      </SceneObject>
      <SceneObject name="Friends">
        <Translation x="64.346" y="8.396" z="-6.737"/>
        <Scale x="0.8" y="0.8" z="0.8"/>
        <Import filename="shared/diorama/common/scenes/portrait/portrait_friends.xml"/>
      </SceneObject>
    </SceneObject>
  </SceneObject>
</Scene>
